AUTHOR.txt
CHANGES.txt
LICENSE.txt
MANIFEST.in
README.txt
bootstrap.py
buildout.cfg
setup.py
version.txt
src/rod/__init__.py
src/rod.recipe.ejabberd.egg-info/PKG-INFO
src/rod.recipe.ejabberd.egg-info/SOURCES.txt
src/rod.recipe.ejabberd.egg-info/dependency_links.txt
src/rod.recipe.ejabberd.egg-info/entry_points.txt
src/rod.recipe.ejabberd.egg-info/namespace_packages.txt
src/rod.recipe.ejabberd.egg-info/not-zip-safe
src/rod.recipe.ejabberd.egg-info/requires.txt
src/rod.recipe.ejabberd.egg-info/top_level.txt
src/rod/recipe/__init__.py
src/rod/recipe/ejabberd/README.txt
src/rod/recipe/ejabberd/__init__.py
src/rod/recipe/ejabberd/tests/__init__.py
src/rod/recipe/ejabberd/tests/test_doc.py